{
    "flag":1,
    "msg": "",
    "data": {
        "last_time":120,
        "programs": [
            { "id": "1", "name": "一", "performer": "集体", "vote_number": "0" },
            { "id": "2", "name": "二", "performer": "团队", "vote_number": "0" },
            { "id": "3", "name": "三", "performer": "团队", "vote_number": "0" },
            { "id": "4", "name": "五", "performer": "个人", "vote_number": "0" },
            { "id": "5", "name": "节目五", "performer": "团队", "vote_number": "0" },
            { "id": "6", "name": "节目六", "performer": "团队", "vote_number": "0" },
            { "id": "7", "name": "节目七", "performer": "团队", "vote_number": "0" },
            { "id": "8", "name": "节目八", "performer": "团队", "vote_number": "0" },
            { "id": "9", "name": "节目九", "performer": "团队", "vote_number": "0" }
        ]
    }
}
